setup.py
asa_hmi_data_agent/__init__.py
asa_hmi_data_agent/__main__.py
asa_hmi_data_agent/listport.py
asa_hmi_data_agent/mainwindow.py
asa_hmi_data_agent/socket_api.py
asa_hmi_data_agent/util.py
asa_hmi_data_agent.egg-info/PKG-INFO
asa_hmi_data_agent.egg-info/SOURCES.txt
asa_hmi_data_agent.egg-info/dependency_links.txt
asa_hmi_data_agent.egg-info/entry_points.txt
asa_hmi_data_agent.egg-info/not-zip-safe
asa_hmi_data_agent.egg-info/requires.txt
asa_hmi_data_agent.egg-info/top_level.txt
asa_hmi_data_agent/adt_settings/__init__.py
asa_hmi_data_agent/adt_settings/__main__.py
asa_hmi_data_agent/adt_settings/adt_settings.py
asa_hmi_data_agent/asaloader/__init__.py
asa_hmi_data_agent/asaloader/__main__.py
asa_hmi_data_agent/asaloader/loader.py
asa_hmi_data_agent/avrdude/__init__.py
asa_hmi_data_agent/avrdude/__main__.py
asa_hmi_data_agent/avrdude/avrdude.py
asa_hmi_data_agent/avrdude/avrdudeConfParser.py
asa_hmi_data_agent/cli_tools/__init__.py
asa_hmi_data_agent/cli_tools/__main__.py
asa_hmi_data_agent/cli_tools/commands.py
asa_hmi_data_agent/cli_tools/socket_handler.py
asa_hmi_data_agent/cli_tools/tool_loader.py
asa_hmi_data_agent/cli_tools/tool_term.py
asa_hmi_data_agent/hmi/__init__.py
asa_hmi_data_agent/hmi/__main__.py
asa_hmi_data_agent/hmi/data_to_text.py
asa_hmi_data_agent/hmi/hmi.py
asa_hmi_data_agent/hmi/hmi_load_dialog.py
asa_hmi_data_agent/hmi/hmi_save_dialog.py
asa_hmi_data_agent/hmi/text_to_data.py
asa_hmi_data_agent/hmipac/__init__.py
asa_hmi_data_agent/hmipac/__main__.py
asa_hmi_data_agent/hmipac/decoder.py
asa_hmi_data_agent/hmipac/encoder.py
asa_hmi_data_agent/hmipac/type.py
asa_hmi_data_agent/settings/avrdude_settings.ini
asa_hmi_data_agent/settings/bits_info.ini
asa_hmi_data_agent/tmp/fuse_extra.txt
asa_hmi_data_agent/tmp/fuse_high.txt
asa_hmi_data_agent/tmp/fuse_low.txt
asa_hmi_data_agent/tmp/lock.txt
asa_hmi_data_agent/tools/avrdude.conf
asa_hmi_data_agent/tools/avrdude.exe
asa_hmi_data_agent/tools/m128_stk500.hex
asa_hmi_data_agent/ui/ui_adt_settings.py
asa_hmi_data_agent/ui/ui_avrdude.py
asa_hmi_data_agent/ui/ui_bit_selector.py
asa_hmi_data_agent/ui/ui_hmi.py
asa_hmi_data_agent/ui/ui_hmi_load_dialog.py
asa_hmi_data_agent/ui/ui_hmi_save_dialog.py
asa_hmi_data_agent/ui/ui_mainwindow.py
asa_hmi_data_agent/ui/ui_widget_asa_loader.py