Metadata-Version: 1.0
Name: asa-hmi-data-agent
Version: 0.5.4
Summary: ASA developing tools on PC.
Home-page: https://github.com/mickey9910326/ASA_HMI_Data_Agent
Author: mickey9910326
Author-email: mickey9910326@gmail.com
License: GPL v3
Platform: UNKNOWN
